MANIFEST.in
README.rst
setup.py
countop/__init__.py
countop/integer.py
countop.egg-info/PKG-INFO
countop.egg-info/SOURCES.txt
countop.egg-info/dependency_links.txt
countop.egg-info/not-zip-safe
countop.egg-info/top_level.txt