Metadata-Version: 1.1
Name: countop
Version: 0.11
Summary: Count basic operations in algorithm implementations.
Home-page: https://github.com/ankur-gupta/countop
Author: Ankur Gupta
Author-email: ankur@perfectlyrandom.org
License: MIT
Keywords: algorithms,count operations
Platform: UNKNOWN
Classifier: Development Status :: 3 - Alpha
Classifier: Programming Language :: Python :: 2.7
